README.md
setup.py
catsHTM/__init__.py
catsHTM/celestial.py
catsHTM/class_HDF5.py
catsHTM/params.py
catsHTM/script.py
catsHTM.egg-info/PKG-INFO
catsHTM.egg-info/SOURCES.txt
catsHTM.egg-info/dependency_links.txt
catsHTM.egg-info/requires.txt
catsHTM.egg-info/top_level.txt